setup.py
metaparser/__init__.py
metaparser.egg-info/PKG-INFO
metaparser.egg-info/SOURCES.txt
metaparser.egg-info/dependency_links.txt
metaparser.egg-info/top_level.txt