Metadata-Version: 1.0
Name: metaparser
Version: 0.0.3
Summary: this is parser of HTML meta tag
Home-page: http://github.com/satoshun/metaparser
Author: satoshun
Author-email: shun.sato1@gmail.com
License: MIT
Platform: UNKNOWN
